wishbone/__init__.py
wishbone/autocomplete_entry.py
wishbone/core.py
wishbone/version.py
wishbone/wb.py
wishbone/wishbone_gui.py
wishbone_dev-0.5.2.data/scripts/wishbone_gui.py
wishbone_dev-0.5.2.dist-info/LICENSE
wishbone_dev-0.5.2.dist-info/METADATA
wishbone_dev-0.5.2.dist-info/WHEEL
wishbone_dev-0.5.2.dist-info/top_level.txt
wishbone_dev-0.5.2.dist-info/RECORD
