Metadata-Version: 2.1
Name: wishbone-dev
Version: 0.5.2
Summary: Wishbone algorithm for identifying bifurcating trajectories from single-cell data
Home-page: UNKNOWN
Author: Manu Setty
Author-email: manu.talanki@gmail.com
License: UNKNOWN
Platform: UNKNOWN
Classifier: Programming Language :: Python :: 3
Classifier: License :: OSI Approved :: MIT License
Classifier: Operating System :: OS Independent
Classifier: Operating System :: POSIX :: Linux
Classifier: Development Status :: 5 - Production/Stable
Classifier: Topic :: Scientific/Engineering :: Bio-Informatics
Classifier: Topic :: Scientific/Engineering :: Visualization
Requires-Python: >=3.6
Requires-Dist: numpy (>=1.12.0)
Requires-Dist: pandas (>=0.19.2)
Requires-Dist: scipy (>=0.18.1)
Requires-Dist: Cython
Requires-Dist: bhtsne
Requires-Dist: matplotlib (>=2.0.0)
Requires-Dist: seaborn (>=0.7.1)
Requires-Dist: sklearn
Requires-Dist: networkx (>=1.11)
Requires-Dist: fcsparser (>=0.1.2)
Requires-Dist: statsmodels (>=0.8.0)
